notionai/__init__.py
notionai/enums.py
notionai/notionai.py
notionai_py-0.1.6.dist-info/LICENSE
notionai_py-0.1.6.dist-info/METADATA
notionai_py-0.1.6.dist-info/WHEEL
notionai_py-0.1.6.dist-info/top_level.txt
notionai_py-0.1.6.dist-info/RECORD
