Metadata-Version: 2.1
Name: notionai-py
Version: 0.1.6
Summary: Unoffical Notion AI API
Author-email: Vaayne <liu.vaayne@gmail.com>
License: MIT License
Project-URL: Homepage, https://github.com/Vaayne/NotionAI
Project-URL: Bug Tracker, https://github.com/Vaayne/NotionAI/issues
Classifier: Programming Language :: Python :: 3
Requires-Python: >=3
License-File: LICENSE
Requires-Dist: requests >=2.18.4
